zdppy_nacos/__init__.py
zdppy_nacos/client.py
zdppy_nacos/commons.py
zdppy_nacos/exception.py
zdppy_nacos/files.py
zdppy_nacos/listener.py
zdppy_nacos/params.py
zdppy_nacos/timer.py
zdppy_nacos-0.1.0.dist-info/LICENSE
zdppy_nacos-0.1.0.dist-info/WHEEL
zdppy_nacos-0.1.0.dist-info/METADATA
zdppy_nacos-0.1.0.dist-info/RECORD
